blask/Dockerfile_template
blask/__init__.py
blask/blaskapp.py
blask/blaskcli.py
blask/blasksettings.py
blask/blogrenderer.py
blask/default_404.md
blask/default_env.env
blask/errors.py
blask/index_template.html
blask/markdown_template.md
blask-0.2.3.dist-info/LICENSE
blask-0.2.3.dist-info/METADATA
blask-0.2.3.dist-info/WHEEL
blask-0.2.3.dist-info/entry_points.txt
blask-0.2.3.dist-info/top_level.txt
blask-0.2.3.dist-info/RECORD
