Metadata-Version: 2.1
Name: blask
Version: 0.2.3
Summary: A simple Blog engine using Flask and Markdown.
Home-page: https://getblask.com
Author: zerasul
Author-email: zerasul@gmail.com
License: GPL 3.0
Platform: UNKNOWN
Classifier: Development Status :: 4 - Beta
Classifier: Topic :: Internet :: WWW/HTTP :: Dynamic Content :: News/Diary
Classifier: Programming Language :: Python :: 3.6
Classifier: Programming Language :: Python :: 3.7
Classifier: Programming Language :: Python :: 3.8
Classifier: Programming Language :: Python :: 3.9
Requires-Python: >=3.6
Requires-Dist: flask
Requires-Dist: markdown
Requires-Dist: Pygments
Requires-Dist: click
